["total_annotation:5864","over_species:16","update_time:Wed Oct 15 05:16:12 EDT 2014",[{"title":"Recently annotated species","details":[{"species":"Ceratitis capitata","abbr":"cercap","annotations":"761","last_modified":"15 Oct 2014","end_date":"Ongoing","ftypes":[{"name":"gene","num":648,"subtypes":[{"name":"gene_mRNA","num":747,"subtypes":[]}]},{"name":"pseudogene","num":14,"subtypes":[{"name":"pseudogene_transcript","num":14,"subtypes":[]}]}]},{"species":"Leptinotarsa decemlineata","abbr":"lepdec","annotations":"549","last_modified":"14 Oct 2014","end_date":"Ongoing","ftypes":[{"name":"gene","num":526,"subtypes":[{"name":"gene_mRNA","num":549,"subtypes":[]}]}]},{"species":"Eurytemora affinis","abbr":"euraff","annotations":"691","last_modified":"13 Oct 2014","end_date":"Ongoing","ftypes":[{"name":"gene","num":651,"subtypes":[{"name":"gene_mRNA","num":691,"subtypes":[]}]}]},{"species":"Frankliniella occidentalis","abbr":"fraocc","annotations":"217","last_modified":"13 Oct 2014","end_date":"Ongoing","ftypes":[{"name":"gene","num":208,"subtypes":[{"name":"gene_mRNA","num":214,"subtypes":[]}]},{"name":"pseudogene","num":3,"subtypes":[{"name":"pseudogene_transcript","num":3,"subtypes":[]}]}]},{"species":"Gerris buenoi","abbr":"gerbue","annotations":"7","last_modified":"9 Oct 2014","end_date":"Ongoing","ftypes":[{"name":"gene","num":6,"subtypes":[{"name":"gene_mRNA","num":7,"subtypes":[]}]}]},{"species":"Oncopeltus fasciatus","abbr":"oncfas","annotations":"1431","last_modified":"7 Oct 2014","end_date":"Ongoing","ftypes":[{"name":"gene","num":1262,"subtypes":[{"name":"gene_mRNA","num":1417,"subtypes":[]},{"name":"gene_rRNA","num":3,"subtypes":[]}]},{"name":"pseudogene","num":11,"subtypes":[{"name":"pseudogene_transcript","num":11,"subtypes":[]}]}]},{"species":"Athalia rosae","abbr":"athros","annotations":"385","last_modified":"7 Oct 2014","end_date":"Ongoing","ftypes":[{"name":"gene","num":348,"subtypes":[{"name":"gene_mRNA","num":385,"subtypes":[]}]}]},{"species":"maydes","abbr":"maydes","annotations":"1","last_modified":"6 Oct 2014","end_date":"Ongoing","ftypes":[{"name":"gene","num":1,"subtypes":[{"name":"gene_mRNA","num":1,"subtypes":[]}]}]},{"species":"Ladona fulva","abbr":"ladful","annotations":"84","last_modified":"5 Oct 2014","end_date":"Ongoing","ftypes":[{"name":"gene","num":61,"subtypes":[{"name":"gene_mRNA","num":79,"subtypes":[]}]},{"name":"pseudogene","num":3,"subtypes":[{"name":"pseudogene_transcript","num":3,"subtypes":[]},{"name":"pseudogene_mRNA","num":2,"subtypes":[]}]}]},{"species":"Ephemera danica","abbr":"ephdan","annotations":"19","last_modified":"5 Oct 2014","end_date":"Ongoing","ftypes":[{"name":"gene","num":19,"subtypes":[{"name":"gene_mRNA","num":19,"subtypes":[]}]}]},{"species":"Orussus abietinus","abbr":"oruabi","annotations":"247","last_modified":"2 Oct 2014","end_date":"Ongoing","ftypes":[{"name":"gene","num":193,"subtypes":[{"name":"gene_mRNA","num":247,"subtypes":[]}]}]},{"species":"Anoplophora glabripennis","abbr":"anogla","annotations":"1270","last_modified":"16 Sep 2014","end_date":"Ongoing","ftypes":[{"name":"gene","num":1097,"subtypes":[{"name":"gene_mRNA","num":1190,"subtypes":[]}]},{"name":"pseudogene","num":54,"subtypes":[{"name":"pseudogene_transcript","num":56,"subtypes":[]},{"name":"pseudogene_mRNA","num":23,"subtypes":[]}]},{"name":"repeat_region","num":1,"subtypes":[]}]},{"species":"Parasteatoda tepidariorum","abbr":"partep","annotations":"13","last_modified":"15 Sep 2014","end_date":"Ongoing","ftypes":[{"name":"gene","num":13,"subtypes":[{"name":"gene_mRNA","num":13,"subtypes":[]}]}]},{"species":"Trichogramma pretiosum","abbr":"tripre","annotations":"128","last_modified":"17 Jul 2014","end_date":"Ongoing","ftypes":[{"name":"gene","num":85,"subtypes":[{"name":"gene_mRNA","num":128,"subtypes":[]}]}]},{"species":"Diaphorina citri","abbr":"diacit","annotations":"45","last_modified":"30 Jun 2014","end_date":"Ongoing","ftypes":[{"name":"gene","num":45,"subtypes":[{"name":"gene_mRNA","num":45,"subtypes":[]}]}]},{"species":"Pachypsylla venusta","abbr":"pacven","annotations":"16","last_modified":"30 Jun 2014","end_date":"Ongoing","ftypes":[{"name":"gene","num":16,"subtypes":[{"name":"gene_mRNA","num":16,"subtypes":[]}]}]}]}]]